<PhotonMainWin>
    <MenuBar>
        <Menu>
            <Action>
                <Title>test1</Title>
                <XmlPath/>
                <IconPath/>
                <Prompt>test prompt1</Prompt>
            </Action>
            <Action>
                <Title>test2</Title>
                <XmlPath/>
                <IconPath/>
                <Prompt>test prompt2</Prompt>
            </Action>
        </Menu>
    </MenuBar>
    <ToolBar/>
    <IconPathList><IconPath>./icons/user_define/1.jpg</IconPath>
        <IconPath>./icons/user_define/2.jpg</IconPath>
        <IconPath>./icons/user_define/3.jpg</IconPath>
        <IconPath>./icons/user_define/4.jpg</IconPath>
        <IconPath>./icons/user_define/5.jpg</IconPath>
    </IconPathList>
	<ItemBox>
		<Assem>
        <Name>a01</Name>
        <Start>assem_55</Start>
        <Next/>
        <Pos>50,50</Pos>
        <StartPos>438,-11</StartPos>
        <EndPos>498,656</EndPos>
        <Sub>
            <If>
                <Name>if01</Name>
                <Next>sleep01</Next>
                <Else>set_1</Else>
                <Pos>273,158</Pos>
                <Operator>130</Operator>
                <Statement1>Local_aaa</Statement1>
                <Statement2>5000</Statement2>
            </If>
            <Sleep>
                <Name>sleep01</Name>
                <Next>set_0</Next>
                <Pos>513,259</Pos>
                <Sleep>10</Sleep>
            </Sleep>
            <Set>
                <Name>set_0</Name>
                <Next>set_2</Next>
                <Pos>401,327</Pos>
                <VarName>Local_aaa</VarName>
                <Statement>Local_aaa+1</Statement>
            </Set>
            <Set>
                <Name>set_1</Name>
                <Next>virtualendflocha</Next>
                <Pos>280,437</Pos>
                <VarName>Local_aaa</VarName>
                <Statement>Local_aaa-1</Statement>
            </Set>
            <Assem>
                <Name>assem_55</Name>
                <Next>if01</Next>
                <Pos>549,107</Pos>
                <Start>set_1_1</Start>
                <Sub>
                    <Set>
                        <Name>set_1_1</Name>
                        <Next>set_1_2</Next>
                        <Pos>90,190</Pos>
                        <VarName>Local_aaa</VarName>
                        <Statement>1000</Statement>
                    </Set>
                    <If>
                        <Name>if_1_1</Name>
                        <Next>virtualendflocha</Next>
                        <Pos>211,500</Pos>
                        <Else>set_1_2</Else>
                        <Operator>66</Operator>
                        <Statement1>Local_aaa</Statement1>
                        <Statement2>100</Statement2>
                    </If>
                    <Set>
                        <Name>set_1_2</Name>
                        <Next>if_1_1</Next>
                        <Pos>126,329</Pos>
                        <VarName>Local_aaa</VarName>
                        <Statement>Local_aaa-1</Statement>
                    </Set>
                </Sub>
                <StartPos>200,50</StartPos>
                <EndPos>455,613</EndPos>
                <LoopRunTimes>0</LoopRunTimes>
                <SleepPerLoop>0</SleepPerLoop>
                <LoopRunCntStr>LoopRunCnt2</LoopRunCntStr>
            </Assem>
            <Set>
                <Name>set_2</Name>
                <Next>if01</Next>
                <Pos>449,455</Pos>
                <VarName>Local_bbb</VarName>
                <Statement>100*sin(Local_aaa*3.1415926/30)</Statement>
            </Set>
        </Sub>
        <LoopRunTimes>0</LoopRunTimes>
        <SleepPerLoop>0</SleepPerLoop>
        <LoopRunCntStr>LoopRunCnt1</LoopRunCntStr>
		</Assem>
	
		<Assem>
                <Name>assem_99</Name>
                <Next>if01</Next>
                <Pos>549,107</Pos>
                <Start>set_1_1</Start>
                <Sub>
                    <Set>
                        <Name>set_1_1</Name>
                        <Next>set_1_2</Next>
                        <Pos>90,190</Pos>
                        <VarName>Local_aaa</VarName>
                        <Statement>1000</Statement>
                    </Set>
                    <If>
                        <Name>if_1_1</Name>
                        <Next>virtualendflocha</Next>
                        <Pos>211,500</Pos>
                        <Else>set_1_2</Else>
                        <Operator>66</Operator>
                        <Statement1>Local_aaa</Statement1>
                        <Statement2>100</Statement2>
                    </If>
                    <Set>
                        <Name>set_1_2</Name>
                        <Next>if_1_1</Next>
                        <Pos>126,329</Pos>
                        <VarName>Local_aaa</VarName>
                        <Statement>Local_aaa-1</Statement>
                    </Set>
                </Sub>
                <StartPos>200,50</StartPos>
                <EndPos>455,613</EndPos>
                <LoopRunTimes>0</LoopRunTimes>
                <SleepPerLoop>0</SleepPerLoop>
                <LoopRunCntStr>LoopRunCnt2</LoopRunCntStr>
        </Assem>
	
	</ItemBox>
	
	
</PhotonMainWin>
